gen_commit/__init__.py
gen_commit/cli.py
gen_commit/git_utils.py
gen_commit/groq_client.py
gen_commit_cli-0.1.1.dist-info/licenses/LICENSE
gen_commit_cli-0.1.1.dist-info/METADATA
gen_commit_cli-0.1.1.dist-info/WHEEL
gen_commit_cli-0.1.1.dist-info/entry_points.txt
gen_commit_cli-0.1.1.dist-info/top_level.txt
gen_commit_cli-0.1.1.dist-info/RECORD
