Metadata-Version: 2.4
Name: gen-commit-cli
Version: 0.1.1
Summary: Generate git commit messages using Groq LLMs
Author: Pankaj Shrivastava
License: MIT
Requires-Python: >=3.9
License-File: LICENSE
Requires-Dist: requests
Requires-Dist: typer
Dynamic: license-file
